{
    "stations": [
    {
        "id": "60500014",
        "name": "solarCity",
        "led": 0,
        "coordinates": [
          14.364339,
          48.256263
        ]
    },
    {
        "id": "60500296",
        "name": "solarCity-Zentrum",
        "led": 0,
        "coordinates": [
          14.361242,
          48.25737
        ]
    },
    {
        "id": "60500015",
        "name": "Neufelderstra\u00dfe",
        "led": 1,
        "coordinates": [
          14.357014790411,
          48.256068209457
        ]
    },
    {
        "id": "60500470",
        "name": "Bahnhof Ebelsberg",
        "led": 2,
        "coordinates": [
          14.347533472669,
          48.252159145863
        ]
    },
    {
        "id": "60500450",
        "name": "Hillerstra\u00dfe",
        "led": 3,
        "coordinates": [
          14.340390416907,
          48.24805469064
        ]
    },
    {
        "id": "60500460",
        "name": "Kaserne",
        "led": 4,
        "coordinates": [
          14.339365977542,
          48.244863287396
        ]
    },
    {
        "id": "60500313",
        "name": "Ennsfeld",
        "led": 5,
        "coordinates": [
          14.33769101074,
          48.242979199718
        ]
    },
    {
        "id": "60502380",
        "name": "Hartheimerstra\u00dfe",
        "led": 6,
        "coordinates": [
          14.334492471349,
          48.240742489834
        ]
    },
    {
        "id": "60500314",
        "name": "Edmund-Aigner-Stra\u00dfe",
        "led": 6,
        "coordinates": [
          14.331698,
          48.24052
        ]
    },
    {
        "id": "60500315",
        "name": "Wambacher Stra\u00dfe",
        "led": 7,
        "coordinates": [
          14.328236128215,
          48.241155051772
        ]
    },
    {
        "id": "60501480",
        "name": "Hauderweg",
        "led": 7,
        "coordinates": [
          14.328708667095,
          48.243585715938
        ]
    },
    {
        "id": "60500410",
        "name": "Ebelsberg",
        "led": 8,
        "coordinates": [
          14.32771397005,
          48.24594374376
        ]
    },
    {
        "id": "60500321",
        "name": "Saporoshjestra\u00dfe",
        "led": 9,
        "coordinates": [
          14.322811003072,
          48.251808792638
        ]
    },
    {
        "id": "60501810",
        "name": "Auwiesen",
        "led": 10,
        "coordinates": [
          14.308497960172,
          48.248908813016
        ]
    },
    {
        "id": "60501590",
        "name": "R\u00e4dlerweg",
        "led": 11,
        "coordinates": [
          14.311577998862,
          48.250953152213
        ]
    },
    {
        "id": "60501520",
        "name": "Dauphinestra\u00dfe",
        "led": 11,
        "coordinates": [
          14.314152839255,
          48.252919603258
        ]
    },
    {
        "id": "60501310",
        "name": "D\u00fcrerstra\u00dfe",
        "led": 12,
        "coordinates": [
          14.317952377592,
          48.254133615247
        ]
    },
    {
        "id": "60501150",
        "name": "Simonystra\u00dfe",
        "led": 13,
        "coordinates": [
          14.322450219249,
          48.255675881278
        ]
    },
    {
        "id": "60501110",
        "name": "Remise Kleinm\u00fcnchen",
        "led": 14,
        "coordinates": [
          14.321232,
          48.258185
        ]
    },
    {
        "id": "60501040",
        "name": "Wimmerstra\u00dfe",
        "led": 15,
        "coordinates": [
          14.319722,
          48.261404
        ]
    },
    {
        "id": "60501210",
        "name": "Wahringerstra\u00dfe",
        "led": 15,
        "coordinates": [
          14.317962,
          48.26509
        ]
    },
    {
        "id": "60501140",
        "name": "Scharlinz",
        "led": 16,
        "coordinates": [
          14.316284,
          48.26874
        ]
    },
    {
        "id": "60501070",
        "name": "Neue Welt",
        "led": 17,
        "coordinates": [
          14.314232,
          48.27309
        ]
    },
    {
        "id": "60501500",
        "name": "voestalpine",
        "led": 18,
        "coordinates": [
          14.312813661316,
          48.276019800002
        ]
    },
    {
        "id": "60501200",
        "name": "WIFI\/LINZ AG",
        "led": 19,
        "coordinates": [
          14.308964712542,
          48.280655891519
        ]
    },
    {
        "id": "60500950",
        "name": "Bulgariplatz",
        "led": 20,
        "coordinates": [
          14.302970890281,
          48.284769516121
        ]
    },
    {
        "id": "60501000",
        "name": "Herz-Jesu-Kirche",
        "led": 20,
        "coordinates": [
          14.300414294642,
          48.287071497004
        ]
    },
    {
        "id": "60501170",
        "name": "Unionkreuzung",
        "led": 21,
        "coordinates": [
          14.2973919838,
          48.29035148197
        ]
    },
    {
        "id": "60501660",
        "name": "Doblerholz",
        "led": 22,
        "coordinates": [
          14.251878,
          48.256963
        ]
    },
    {
        "id": "60501750",
        "name": "Harterfeldsiedlung",
        "led": 23,
        "coordinates": [
          14.255920207547,
          48.260068226415
        ]
    },
    {
        "id": "60500120",
        "name": "Meixnerkreuzung",
        "led": 24,
        "coordinates": [
          14.258940134262,
          48.262732683295
        ]
    },
    {
        "id": "60500046",
        "name": "Poststra\u00dfe",
        "led": 25,
        "coordinates": [
          14.264930401222,
          48.267814042337
        ]
    },
    {
        "id": "60500090",
        "name": "Haag",
        "led": 25,
        "coordinates": [
          14.267233099264,
          48.26967270266
        ]
    },
    {
        "id": "60500081",
        "name": "Larnhauserweg",
        "led": 25,
        "coordinates": [
          14.273331111072,
          48.275057253129
        ]
    },
    {
        "id": "60500080",
        "name": "Gaumberg",
        "led": 26,
        "coordinates": [
          14.276470809295,
          48.277643061552
        ]
    },
    {
        "id": "60500150",
        "name": "Untergaumberg",
        "led": 27,
        "coordinates": [
          14.279421948039,
          48.27950319751
        ]
    },
    {
        "id": "60501720",
        "name": "Hauptbahnhof",
        "led": 28,
        "coordinates": [
          14.291135,
          48.291134
        ]
    },
    {
        "id": "60500990",
        "name": "Goethekreuzung",
        "led": 29,
        "coordinates": [
          14.292092,
          48.29597
        ]
    },
    {
        "id": "60500940",
        "name": "B\u00fcrgerstra\u00dfe",
        "led": 30,
        "coordinates": [
          14.291480877914,
          48.298165388621
        ]
    },
    {
        "id": "60501060",
        "name": "Mozartkreuzung",
        "led": 31,
        "coordinates": [
          14.290388,
          48.301238
        ]
    },
    {
        "id": "60501160",
        "name": "Taubenmarkt",
        "led": 32,
        "coordinates": [
          14.288369885517,
          48.303782236596
        ]
    },
    {
        "id": "60501010",
        "name": "Hauptplatz",
        "led": 33,
        "coordinates": [
          14.286230584182,
          48.306263243503
        ]
    },
    {
        "id": "60501700",
        "name": "Landgutstra\u00dfe",
        "led": 34,
        "coordinates": [
          14.27762,
          48.311078
        ]
    },
    {
        "id": "60501730",
        "name": "M\u00fchlkreisbahnhof",
        "led": 35,
        "coordinates": [
          14.280068443853,
          48.311896388183
        ]
    },
    {
        "id": "60501710",
        "name": "Biegung",
        "led": 36,
        "coordinates": [
          14.281806094728,
          48.312557582618
        ]
    },
    {
        "id": "60501100",
        "name": "Rudolfstra\u00dfe",
        "led": 37,
        "coordinates": [
          14.283006017353,
          48.310819385822
        ]
    },
    {
        "id": "60501190",
        "name": "Wildbergstra\u00dfe",
        "led": 38,
        "coordinates": [
          14.286980769106,
          48.313103600584
        ]
    },
    {
        "id": "60501090",
        "name": "Peuerbachstra\u00dfe",
        "led": 39,
        "coordinates": [
          14.289712875385,
          48.315746915473
        ]
    },
    {
        "id": "60501050",
        "name": "Linke Br\u00fcckenstra\u00dfe",
        "led": 40,
        "coordinates": [
          14.289654062295,
          48.319931514754
        ]
    },
    {
        "id": "60501080",
        "name": "Ontlstra\u00dfe",
        "led": 41,
        "coordinates": [
          14.285120499259,
          48.322669435589
        ]
    },
    {
        "id": "60501030",
        "name": "Harbach",
        "led": 42,
        "coordinates": [
          14.285046014476,
          48.327232415603
        ]
    },
    {
        "id": "60501020",
        "name": "Harbachsiedlung",
        "led": 42,
        "coordinates": [
          14.287914,
          48.329911
        ]
    },
    {
        "id": "60500980",
        "name": "Gr\u00fcndberg",
        "led": 43,
        "coordinates": [
          14.290310169883,
          48.332552448087
        ]
    },
    {
        "id": "60500346",
        "name": "Ferdinand Markl Stra\u00dfe",
        "led": 44,
        "coordinates": [
          14.296597055379,
          48.334128237842
        ]
    },
    {
        "id": "60501130",
        "name": "St. Magdalena",
        "led": 45,
        "coordinates": [
          14.301059783019,
          48.334145990566
        ]
    },
    {
        "id": "60500970",
        "name": "Glaserstra\u00dfe",
        "led": 46,
        "coordinates": [
          14.309156499363,
          48.332603758769
        ]
    },
    {
        "id": "60500960",
        "name": "Dornach",
        "led": 47,
        "coordinates": [
          14.312502858862,
          48.331850194057
        ]
    },
    {
        "id": "60501120",
        "name": "Schumpeterstra\u00dfe",
        "led": 48,
        "coordinates": [
          14.317783914406,
          48.332149908674
        ]
    },
    {
        "id": "60500920",
        "name": "JKU | Universit\u00e4t",
        "led": 49,
        "coordinates": [
          14.320391,
          48.334874
        ]
    }
    ]
}
